README.rst
setup.py
login/__init__.py
login/check.py
login.egg-info/PKG-INFO
login.egg-info/SOURCES.txt
login.egg-info/dependency_links.txt
login.egg-info/top_level.txt