Metadata-Version: 2.1
Name: login
Version: 0.0.1
Summary: Module for common login service
Home-page: https://github.com/ksg97031/login
Author: ksg97031
Author-email: ksg97031@gmail.com
License: UNKNOWN
Platform: UNKNOWN
Classifier: Programming Language :: Python :: 3
Classifier: License :: OSI Approved :: MIT License
Classifier: Operating System :: OS Independent
Requires-Python: >=3
